codebuilder/__init__.py
codebuilder/cli.py
codebuilder/codebuilder-complete.sh
codebuilder/helpers/__init__.py
codebuilder/helpers/aws.py
codebuilder/helpers/base.py
codebuilder/helpers/docker.py
codebuilder/subcommands/__init__.py
codebuilder/subcommands/aws.py
codebuilder/subcommands/docker.py
codebuilder/subcommands/github.py
codebuilder-0.0.1a3.dist-info/DESCRIPTION.rst
codebuilder-0.0.1a3.dist-info/METADATA
codebuilder-0.0.1a3.dist-info/RECORD
codebuilder-0.0.1a3.dist-info/WHEEL
codebuilder-0.0.1a3.dist-info/entry_points.txt
codebuilder-0.0.1a3.dist-info/metadata.json
codebuilder-0.0.1a3.dist-info/top_level.txt
